{
  "resource": "Create vk group",
  "resource_explanation": null,
  "http_method": "POST",
  "route": "api/v1/vk/groups",
  "description": "Success",
  "explanation": null,
  "parameters": [
    {
      "type": "string",
      "in": "body",
      "required": true,
      "name": "group_id",
      "description": "Vk group id"
    },
    {
      "type": "string",
      "in": "body",
      "required": true,
      "name": "confirmation_code",
      "description": "Confirmation code (use this code for link for callback api: https://fathomless-earth-40434.herokuapp.com/api/test/v1/vk/callback/<company_id>/<code>) "
    },
    {
      "type": "integer",
      "minmum": 0,
      "maximum": 10000000000,
      "in": "body",
      "required": true,
      "name": "group_join_points",
      "description": "Group join"
    },
    {
      "type": "integer",
      "minmum": 0,
      "maximum": 10000000000,
      "in": "body",
      "required": true,
      "name": "wall_repost_points",
      "description": "Repost"
    },
    {
      "type": "integer",
      "minmum": 0,
      "maximum": 10000000000,
      "in": "body",
      "required": true,
      "name": "wall_like_points",
      "description": "Post like"
    },
    {
      "type": "integer",
      "minmum": 0,
      "maximum": 10000000000,
      "in": "body",
      "required": true,
      "name": "wall_reply_points",
      "description": "Post comment"
    },
    {
      "type": "integer",
      "required": true,
      "name": "company_id",
      "description": "Company id"
    }
  ],
  "response_fields": [

  ],
  "requests": [
    {
      "request_method": "POST",
      "request_path": "api/v1/vk/groups",
      "request_body": "{\"group_id\":\"123\",\"confirmation_code\":\"45857340\",\"group_join_points\":1000,\"wall_repost_points\":1000,\"wall_like_points\":1000,\"wall_reply_points\":1000,\"company_id\":36181}",
      "request_headers": {
        "Content-Type": "application/json",
        "Authorization": "eyJhbGciOiJIUzI1NiJ9.eyJ1c2VyX2lkIjo3ODE3Nn0.zN24ojdAJQYV-pyWgkjgpBFHqiZ7G1-AHjmVI86ooSQ",
        "Host": "example.org",
        "Cookie": ""
      },
      "request_query_parameters": {
      },
      "request_content_type": "application/json",
      "response_status": 200,
      "response_status_text": "OK",
      "response_body": "{\n  \"id\": 16,\n  \"company_id\": 36181,\n  \"confirmation_code\": \"45857340\",\n  \"confirmed\": false,\n  \"callback_code\": \"91802c85b\",\n  \"created_at\": \"2020-03-19T10:19:25.980Z\",\n  \"updated_at\": \"2020-03-19T10:19:25.980Z\",\n  \"group_id\": \"123\",\n  \"group_join_points\": 1000,\n  \"wall_repost_points\": 1000,\n  \"wall_like_points\": 1000,\n  \"wall_reply_points\": 1000\n}",
      "response_headers": {
        "Content-Type": "application/json; charset=utf-8",
        "ETag": "W/\"857e556a33b4c0bd8574d98d51f7dd78\"",
        "Cache-Control": "max-age=0, private, must-revalidate",
        "X-Request-Id": "f2818f43-38f3-4f56-866a-8fa638cbdd42",
        "X-Runtime": "0.028738",
        "Vary": "Origin",
        "Content-Length": "302"
      },
      "response_content_type": "application/json; charset=utf-8",
      "curl": "curl \"http://localhost:3000api/v1/vk/groups\" -d '{\"group_id\":\"123\",\"confirmation_code\":\"45857340\",\"group_join_points\":1000,\"wall_repost_points\":1000,\"wall_like_points\":1000,\"wall_reply_points\":1000,\"company_id\":36181}' -X POST \\\n\t-H \"Content-Type: application/json\" \\\n\t-H \"Authorization: eyJhbGciOiJIUzI1NiJ9.eyJ1c2VyX2lkIjo3ODE3Nn0.zN24ojdAJQYV-pyWgkjgpBFHqiZ7G1-AHjmVI86ooSQ\" \\\n\t-H \"Host: example.org\" \\\n\t-H \"Cookie: \""
    }
  ]
}