{
  "resource": "List stores",
  "resource_explanation": null,
  "http_method": "GET",
  "route": "api/v1/stores",
  "description": "Success",
  "explanation": null,
  "parameters": [
    {
      "type": "integer",
      "name": "limit",
      "description": "Limit"
    },
    {
      "type": "integer",
      "name": "offset",
      "description": "Offset"
    }
  ],
  "response_fields": [

  ],
  "requests": [
    {
      "request_method": "GET",
      "request_path": "api/v1/stores",
      "request_body": null,
      "request_headers": {
        "Content-Type": "application/json",
        "Authorization": "eyJhbGciOiJIUzI1NiJ9.eyJ1c2VyX2lkIjoyNDEwNiwiZXhwIjoxNTY4OTkyNjU5fQ.7j_IxciEsIaSKlT7BQ7kdrQgpaubSTdstLP0ixTv-Ho",
        "Host": "example.org",
        "Cookie": ""
      },
      "request_query_parameters": {
      },
      "request_content_type": "application/json",
      "response_status": 200,
      "response_status_text": "OK",
      "response_body": "[\n  {\n    \"id\": 7337,\n    \"name\": \"test\",\n    \"company_id\": 11215,\n    \"created_at\": \"2019-09-13T15:17:39.085Z\",\n    \"updated_at\": \"2019-09-13T15:17:39.085Z\",\n    \"country\": \"test\",\n    \"city\": \"test\",\n    \"street\": \"test\",\n    \"house\": \"1\"\n  },\n  {\n    \"id\": 7336,\n    \"name\": \"test\",\n    \"company_id\": 11215,\n    \"created_at\": \"2019-09-13T15:17:39.081Z\",\n    \"updated_at\": \"2019-09-13T15:17:39.081Z\",\n    \"country\": \"test\",\n    \"city\": \"test\",\n    \"street\": \"test\",\n    \"house\": \"1\"\n  },\n  {\n    \"id\": 7335,\n    \"name\": \"test\",\n    \"company_id\": 11215,\n    \"created_at\": \"2019-09-13T15:17:39.078Z\",\n    \"updated_at\": \"2019-09-13T15:17:39.078Z\",\n    \"country\": \"test\",\n    \"city\": \"test\",\n    \"street\": \"test\",\n    \"house\": \"1\"\n  }\n]",
      "response_headers": {
        "Content-Type": "application/json; charset=utf-8",
        "ETag": "W/\"5bc99999b5143fa88cab75fc88e032c8\"",
        "Cache-Control": "max-age=0, private, must-revalidate",
        "X-Request-Id": "5b85e956-a112-4fd0-bfc3-36d3a10cfa1a",
        "X-Runtime": "0.013211",
        "Vary": "Origin",
        "Content-Length": "553"
      },
      "response_content_type": "application/json; charset=utf-8",
      "curl": "curl \"http://localhost:3000api/v1/stores\" -X GET \\\n\t-H \"Content-Type: application/json\" \\\n\t-H \"Authorization: eyJhbGciOiJIUzI1NiJ9.eyJ1c2VyX2lkIjoyNDEwNiwiZXhwIjoxNTY4OTkyNjU5fQ.7j_IxciEsIaSKlT7BQ7kdrQgpaubSTdstLP0ixTv-Ho\" \\\n\t-H \"Host: example.org\" \\\n\t-H \"Cookie: \""
    }
  ]
}